Workbook

Sheet Répartition
B1: Plan média · 1er trimestre 2027 · 40 000 000 F CFA
B2: Huile Dinor, grossistes et boutiques de quartier · du 4 janvier au 31 mars 2027 · montants TTC à confirmer sur devis
A4: Poste | B4: Bloc | C4: Étape du parcours | D4: Montant | E4: Part | F4: Ce que ça achète | G4: Règle de dépense
A5: Club des grossistes : récompenses | B5: Revendeurs | C5: Décision, fidélisation | D5: 8000000 | E5: =D5/$D$14 | F5: Récompenses des trois paliers de commande, en produits Sania ou en équipement de stockage | G5: Paliers fixés par grossiste sur ses achats du 1er trimestre 2026 ; remise contre bon de commande facturé
A6: Habillage des boutiques | B6: Terrain | C6: Considération, décision | D6: 7500000 | E6: =D6/$D$14 | F6: Autocollants de façade, affichettes « Ici, Dinor », réglettes de rayon, présentoirs | G6: Quantités fixées sur devis de deux imprimeurs au moins ; paiement à la livraison
A7: Animatrices et superviseurs | B7: Terrain | C7: Décision | D7: 6000000 | E7: =D7/$D$14 | F7: 12 semaines de visites hebdomadaires, transport compris, relevés chaque soir | G7: Contrat de prestation ; paiement sur relevés de visites remis
A8: Radio de proximité | B8: Médias | C8: Découverte | D8: 5000000 | E8: =D8/$D$14 | F8: Deux vagues et un rappel, tranches du matin et de la mi-journée, dans les villes du plan | G8: Brief identique aux régies ; ordre d'insertion contrôlé ; paiement sur attestation de diffusion
A9: Challenge des boutiquiers : lots | B9: Revendeurs | C9: Décision, fidélisation | D9: 4000000 | E9: =D9/$D$14 | F9: Lots hebdomadaires pendant 5 semaines et un grand prix par ville | G9: Règlement validé avant annonce ; lots remis contre photo et signature
A10: Rencontres des grossistes | B10: Terrain | C10: Découverte, considération | D10: 3000000 | E10: =D10/$D$14 | F10: 6 sessions dans 5 villes : salle, collation, supports, transport de l'équipe | G10: Devis par ville
A11: Facebook, Instagram, TikTok, WhatsApp | B11: Médias | C11: Découverte, considération | D11: 3000000 | E11: =D11/$D$14 | F11: Diffusion des vidéos de recettes et annonces du challenge dans les villes du plan | G11: Plafond quotidien ; arrêt d'une publicité qui ne fait pas réagir au bout de 7 jours
A12: Production | B12: Production | C12: Toutes | D12: 1500000 | E12: =D12/$D$14 | F12: Spot radio en français et en langues locales, 6 vidéos de recettes, maquettes des supports | G12: Paiement sur livraison des fichiers validés
A13: Réserve | B13: Réserve | C13: Selon résultats | D13: 2000000 | E13: =D13/$D$14 | F13: Renfort du canal qui marche le mieux | G13: Débloquée le vendredi 26 février, sur accord écrit
A14: Total | D14: =SUM(D5:D13) | E14: =SUM(E5:E13)
A16: Par bloc
A17: Revendeurs | D17: =SUMIF($B$5:$B$13,A17,$D$5:$D$13) | E17: =D17/$D$14
A18: Terrain | D18: =SUMIF($B$5:$B$13,A18,$D$5:$D$13) | E18: =D18/$D$14
A19: Médias | D19: =SUMIF($B$5:$B$13,A19,$D$5:$D$13) | E19: =D19/$D$14
A20: Production | D20: =SUMIF($B$5:$B$13,A20,$D$5:$D$13) | E20: =D20/$D$14
A21: Réserve | D21: =SUMIF($B$5:$B$13,A21,$D$5:$D$13) | E21: =D21/$D$14

Sheet Calendrier
B1: Calendrier semaine par semaine
B2: Montants engagés par semaine (F CFA) · chaque ligne se recoupe avec l'onglet Répartition
A4: Poste | B4: S1 4-10 janv. | C4: S2 11-17 janv. | D4: S3 18-24 janv. | E4: S4 25-31 janv. | F4: S5 1-7 févr. | G4: S6 8-14 févr. | H4: S7 15-21 févr. | I4: S8 22-28 févr. | J4: S9 1-7 mars | K4: S10 8-14 mars | L4: S11 15-21 mars | M4: S12 22-28 mars | N4: S13 29-31 mars | O4: Total | P4: Contrôle
A5: Temps du plan | B5: Remise en route | C5: Remise en route | D5: Stockage avant le Ramadan | E5: Stockage avant le Ramadan | F5: Stockage avant le Ramadan | G5: Ramadan | H5: Ramadan | I5: Ramadan | J5: Ramadan | K5: Ramadan | L5: Pâques et bilan | M5: Pâques et bilan | N5: Pâques et bilan
A6: Club des grossistes : récompenses | E6: 2000000 | J6: 3000000 | M6: 3000000 | O6: =SUM(B6:N6) | P6: =IF(O6=Répartition!D5,"OK","écart")
A7: Habillage des boutiques | C7: 2500000 | D7: 3000000 | E7: 2000000 | O7: =SUM(B7:N7) | P7: =IF(O7=Répartition!D6,"OK","écart")
A8: Animatrices et superviseurs | B8: 500000 | C8: 500000 | D8: 500000 | E8: 500000 | F8: 500000 | G8: 500000 | H8: 500000 | I8: 500000 | J8: 500000 | K8: 500000 | L8: 500000 | M8: 500000 | O8: =SUM(B8:N8) | P8: =IF(O8=Répartition!D7,"OK","écart")
A9: Radio de proximité | E9: 600000 | F9: 600000 | G9: 600000 | H9: 600000 | I9: 600000 | J9: 600000 | K9: 600000 | M9: 600000 | N9: 200000 | O9: =SUM(B9:N9) | P9: =IF(O9=Répartition!D8,"OK","écart")
A10: Challenge des boutiquiers : lots | G10: 600000 | H10: 600000 | I10: 600000 | J10: 600000 | K10: 1600000 | O10: =SUM(B10:N10) | P10: =IF(O10=Répartition!D9,"OK","écart")
A11: Rencontres des grossistes | C11: 3000000 | O11: =SUM(B11:N11) | P11: =IF(O11=Répartition!D10,"OK","écart")
A12: Facebook, Instagram, TikTok, WhatsApp | D12: 250000 | E12: 250000 | F12: 300000 | G12: 300000 | H12: 300000 | I12: 300000 | J12: 300000 | K12: 300000 | L12: 200000 | M12: 300000 | N12: 200000 | O12: =SUM(B12:N12) | P12: =IF(O12=Répartition!D11,"OK","écart")
A13: Production | B13: 900000 | C13: 400000 | D13: 200000 | O13: =SUM(B13:N13) | P13: =IF(O13=Répartition!D12,"OK","écart")
A14: Réserve | O14: =SUM(B14:N14) | P14: à décider
A15: Total de la semaine | B15: =SUM(B6:B14) | C15: =SUM(C6:C14) | D15: =SUM(D6:D14) | E15: =SUM(E6:E14) | F15: =SUM(F6:F14) | G15: =SUM(G6:G14) | H15: =SUM(H6:H14) | I15: =SUM(I6:I14) | ... O15: =SUM(O6:O14) | P15: =IF(O15=Répartition!D14-Répartition!D13,"OK","écart")
A16: Cumul engagé | B16: =SUM($B$15:B15) | C16: =SUM($B$15:C15) | D16: =SUM($B$15:D15) | E16: =SUM($B$15:E15) | F16: =SUM($B$15:F15) | G16: =SUM($B$15:G15) | H16: =SUM($B$15:H15) | I16: =SUM($B$15:I15) | ... N16: =SUM($B$15:N15)
A18: La réserve n'est pas placée : elle se décide au point du vendredi 26 février (S8).

Sheet Radios
B1: Consultation des radios : brief et grille de comparaison
B2: Le même brief part à toutes les régies consultées, après votre accord. Aucun tarif ni aucune audience n'est supposé ici.
A4: Annonceur | B4: Sania Cie, marque Dinor (huile de palme raffinée)
A5: Objectif | B5: Faire demander Dinor dans les boutiques de quartier pendant le Ramadan et la fête de fin du Ramadan
A6: Cible | B6: Femmes et hommes qui font la cuisine au foyer, 25-55 ans, quartiers populaires et intermédiaires
A7: Zones | B7: Abidjan, Bouaké, San Pedro, Daloa, Korhogo
A8: Période | B8: Vague 1 : 25 janvier au 7 février 2027 · Vague 2 : 8 février au 14 mars 2027 · Rappel : 22 au 31 mars 2027
A9: Format | B9: Spot de 30 secondes en français, et version en langue locale si la station en diffuse
A10: Tranches souhaitées | B10: 6 h - 9 h et 11 h - 14 h, du lundi au samedi ; heure de rupture du jeûne pendant le Ramadan
A11: Enveloppe indicative | B11: 5 000 000 F CFA TTC pour l'ensemble des stations, production non comprise
A12: À indiquer dans la réponse | B12: Stations, tranches exactes, nombre de passages, audience et sa source datée, prix brut, remises, prix net, frais techniques, conditions de paiement et d'annulation, justificatifs de diffusion
A13: Date limite de réponse | B13: ⟦à fixer, au plus tard le 11 décembre 2026⟧
A15: Grille de comparaison (à remplir avec les propositions écrites)
A16: Régie | B16: Station | C16: Ville | D16: Tranches proposées | E16: Passages | F16: Audience (source et date) | G16: Prix net TTC | H16: Frais | I16: Remarques

Sheet Terrain
B1: Le dispositif terrain par ville
B2: Les cases jaunes sont à arrêter avec la direction commerciale ; les quantités suivent les devis
A4: Ville | B4: Grossistes invités | C4: Session de rencontre | D4: Boutiques à équiper | E4: Animatrices | F4: Superviseur | G4: Grossistes inscrits | H4: Boutiques équipées (réalisé)
A5: Abidjan nord (Adjamé, Abobo, Yopougon) | C5: Mar. 12 janvier
A6: Abidjan sud (Treichville, Koumassi, Port-Bouët) | C6: Mer. 13 janvier
A7: Bouaké | C7: Jeu. 14 janvier
A8: San Pedro | C8: Ven. 15 janvier
A9: Daloa | C9: Lun. 11 janvier
A10: Korhogo | C10: Sam. 16 janvier
A11: Total | B11: =SUM(B5:B10) | D11: =SUM(D5:D10) | E11: =SUM(E5:E10) | G11: =SUM(G5:G10) | H11: =SUM(H5:H10)
A13: Fiche de visite (une ligne par visite dans le tableur des relevés)
A14: Date | B14: Animatrice | C14: Boutique et quartier | D14: Formats présents | E14: Ruptures | F14: Prix au client (1 L) | G14: Clients qui demandent Dinor (oui / non) | H14: Commande transmise au grossiste

Sheet Tableau de bord
B1: Tableau de bord hebdomadaire
B2: Une colonne par semaine ; les seuils d'alerte sont ceux du plan marketing
A4: Indicateur | B4: Étape | C4: Seuil | D4: S1 | E4: S2 | F4: S3 | G4: S4 | H4: S5 | I4: S6 | J4: S7 | K4: S8 | L4: S9 | M4: S10 | N4: S11 | O4: S12 | P4: S13
A5: Grossistes inscrits / invités | B5: Considération | C5: 60 %
A6: Commandes des grossistes du club vs même semaine 2026 | B6: Décision | C6: +5 % au 29 janvier
A7: Boutiques équipées / prévues | B7: Considération | C7: 80 % au 7 février
A8: Visites sans rupture des petits formats | B8: Décision | C8: 80 %
A9: Boutiques actives dans le challenge | B9: Fidélisation | C9: 50 % des inscrites
A10: Boutiquiers qui disent que les clients demandent Dinor | B10: Découverte | C10: en hausse entre S1 et S12
A11: Coût par vue de 10 secondes des vidéos | B11: Découverte | C11: coupe des plus chères à 7 jours
A12: Budget engagé cumulé | B12: Pilotage | D12: =Calendrier!B16 | E12: =Calendrier!C16 | F12: =Calendrier!D16 | G12: =Calendrier!E16 | H12: =Calendrier!F16 | I12: =Calendrier!G16 | J12: =Calendrier!H16 | K12: =Calendrier!I16 | ... P12: =Calendrier!N16
