Workbook

Sheet Budget
A1: BRIDGE BANK GROUP
A2: Budget marketing 2027 par canal et par mois (milliers FCFA TTC)
A4: Poste | B4: Canal | C4: Chantier | D4: Étage | E4: Janv. | F4: Févr. | G4: Mars | H4: Avr. | I4: Mai | J4: Juin | K4: Juil. | L4: Août | M4: Sept. | N4: Oct. | O4: Nov. | P4: Déc. | Q4: Total TTC | R4: HT (TVA 18 % à vérifier) | S4: TVA
A5: Publicité en ligne | B5: Meta, Google, LinkedIn | C5: Comptes particuliers et diaspora | D5: Contacts | E5: 11400 | F5: 15200 | G5: 17100 | H5: 13300 | I5: 15200 | J5: 17100 | K5: 13300 | L5: 15200 | M5: 20900 | N5: 19000 | O5: 15200 | P5: 17100 | Q5: =SUM(E5:P5) | R5: =ROUND(Q5/1.18,0) | S5: =Q5-R5
A6: Médias hors ligne | B6: Radio (Abidjan et grandes villes) | C6: Notoriété et comptes | D6: Notoriété | E6: 0 | F6: 10800 | G6: 10800 | H6: 0 | I6: 9000 | J6: 7200 | K6: 0 | L6: 9000 | M6: 14400 | N6: 12600 | O6: 7200 | P6: 9000 | Q6: =SUM(E6:P6) | R6: =ROUND(Q6/1.18,0) | S6: =Q6-R6
A7: Médias hors ligne | B7: Télévision | C7: Notoriété | D7: Notoriété | E7: 0 | F7: 0 | G7: 24000 | H7: 0 | I7: 18000 | J7: 0 | K7: 0 | L7: 18000 | M7: 30000 | N7: 0 | O7: 0 | P7: 30000 | Q7: =SUM(E7:P7) | R7: =ROUND(Q7/1.18,0) | S7: =Q7-R7
A8: Médias hors ligne | B8: Affichage Abidjan | C8: Notoriété et agences | D8: Notoriété | E8: 0 | F8: 0 | G8: 27500 | H8: 0 | I8: 0 | J8: 0 | K8: 0 | L8: 0 | M8: 44000 | N8: 0 | O8: 0 | P8: 38500 | Q8: =SUM(E8:P8) | R8: =ROUND(Q8/1.18,0) | S8: =Q8-R8
A9: Événements et terrain | B9: Forums PME, salons, activations en agence | C9: Clients PME | D9: Contacts | E9: 0 | F9: 4750 | G9: 9500 | H9: 14250 | I9: 9500 | J9: 9500 | K9: 0 | L9: 0 | M9: 9500 | N9: 19000 | O9: 14250 | P9: 4750 | Q9: =SUM(E9:P9) | R9: =ROUND(Q9/1.18,0) | S9: =Q9-R9
A10: Contenus et création | B10: Photos, vidéos, visuels, rédaction | C10: Tous | D10: Tous | E10: 4200 | F10: 5600 | G10: 6300 | H10: 4900 | I10: 5600 | J10: 6300 | K10: 4900 | L10: 5600 | M10: 7700 | N10: 7000 | O10: 5600 | P10: 6300 | Q10: =SUM(E10:P10) | R10: =ROUND(Q10/1.18,0) | S10: =Q10-R10
A11: Relations presse et partenariats | B11: Presse économique, sponsoring | C11: Image et PME | D11: Notoriété | E11: 3000 | F11: 3000 | G11: 6000 | H11: 3000 | I11: 6000 | J11: 6000 | K11: 3000 | L11: 9000 | M11: 6000 | N11: 6000 | O11: 3000 | P11: 6000 | Q11: =SUM(E11:P11) | R11: =ROUND(Q11/1.18,0) | S11: =Q11-R11
A12: Outils | B12: CRM, emailing, site | C12: Fidélisation | D12: Fidélisation | E12: 2916 | F12: 2916 | G12: 2916 | H12: 2916 | I12: 2916 | J12: 2916 | K12: 2916 | L12: 2916 | M12: 2916 | N12: 2916 | O12: 2916 | P12: 2924 | Q12: =SUM(E12:P12) | R12: =ROUND(Q12/1.18,0) | S12: =Q12-R12
A13: Études | B13: Notoriété et satisfaction clients | C13: Mesure | D13: Mesure | E13: 0 | F13: 0 | G13: 12500 | H13: 0 | I13: 0 | J13: 0 | K13: 0 | L13: 0 | M13: 0 | N13: 12500 | O13: 0 | P13: 0 | Q13: =SUM(E13:P13) | R13: =ROUND(Q13/1.18,0) | S13: =Q13-R13
A14: Prestataires | B14: Agence créative et média | C14: Tous | D14: Tous | E14: 3332 | F14: 3332 | G14: 3332 | H14: 3332 | I14: 3332 | J14: 3332 | K14: 3332 | L14: 3332 | M14: 3332 | N14: 3332 | O14: 3332 | P14: 3348 | Q14: =SUM(E14:P14) | R14: =ROUND(Q14/1.18,0) | S14: =Q14-R14
A15: Réserve | B15: Tests et imprévus | E15: 1250 | F15: 1250 | G15: 1250 | H15: 1250 | I15: 1250 | J15: 1250 | K15: 1250 | L15: 1250 | M15: 1250 | N15: 1250 | O15: 1250 | P15: 1250 | Q15: =SUM(E15:P15) | R15: =ROUND(Q15/1.18,0) | S15: =Q15-R15
A16: Total | E16: =SUM(E5:E15) | F16: =SUM(F5:F15) | G16: =SUM(G5:G15) | H16: =SUM(H5:H15) | I16: =SUM(I5:I15) | J16: =SUM(J5:J15) | K16: =SUM(K5:K15) | L16: =SUM(L5:L15) | ... S16: =SUM(S5:S15)
A18: Objectifs et enveloppe fournis par le testeur : fictifs. Montants = enveloppes, à confirmer par devis.

Sheet Revue mensuelle
A1: BRIDGE BANK GROUP
A2: Revue budgétaire : prévu, engagé, facturé, payé
A4: Poste | B4: Canal | C4: Prévu (voté) | D4: Engagé | E4: Facturé | F4: Payé | G4: Écart prévu - engagé | H4: Alerte (seuil 10 %) | I4: Cause et proposition
A5: Publicité en ligne | B5: Meta, Google, LinkedIn | C5: =Budget!Q5 | G5: =C5-D5 | H5: =IF(C5=0,"",IF(ABS(G5)/C5>0.1,"À expliquer",""))
A6: Médias hors ligne | B6: Radio (Abidjan et grandes villes) | C6: =Budget!Q6 | G6: =C6-D6 | H6: =IF(C6=0,"",IF(ABS(G6)/C6>0.1,"À expliquer",""))
A7: Médias hors ligne | B7: Télévision | C7: =Budget!Q7 | G7: =C7-D7 | H7: =IF(C7=0,"",IF(ABS(G7)/C7>0.1,"À expliquer",""))
A8: Médias hors ligne | B8: Affichage Abidjan | C8: =Budget!Q8 | G8: =C8-D8 | H8: =IF(C8=0,"",IF(ABS(G8)/C8>0.1,"À expliquer",""))
A9: Événements et terrain | B9: Forums PME, salons, activations en agence | C9: =Budget!Q9 | G9: =C9-D9 | H9: =IF(C9=0,"",IF(ABS(G9)/C9>0.1,"À expliquer",""))
A10: Contenus et création | B10: Photos, vidéos, visuels, rédaction | C10: =Budget!Q10 | G10: =C10-D10 | H10: =IF(C10=0,"",IF(ABS(G10)/C10>0.1,"À expliquer",""))
A11: Relations presse et partenariats | B11: Presse économique, sponsoring | C11: =Budget!Q11 | G11: =C11-D11 | H11: =IF(C11=0,"",IF(ABS(G11)/C11>0.1,"À expliquer",""))
A12: Outils | B12: CRM, emailing, site | C12: =Budget!Q12 | G12: =C12-D12 | H12: =IF(C12=0,"",IF(ABS(G12)/C12>0.1,"À expliquer",""))
A13: Études | B13: Notoriété et satisfaction clients | C13: =Budget!Q13 | G13: =C13-D13 | H13: =IF(C13=0,"",IF(ABS(G13)/C13>0.1,"À expliquer",""))
A14: Prestataires | B14: Agence créative et média | C14: =Budget!Q14 | G14: =C14-D14 | H14: =IF(C14=0,"",IF(ABS(G14)/C14>0.1,"À expliquer",""))
A15: Réserve | B15: Tests et imprévus | C15: =Budget!Q15 | G15: =C15-D15 | H15: =IF(C15=0,"",IF(ABS(G15)/C15>0.1,"À expliquer",""))

Sheet Temps forts
A1: BRIDGE BANK GROUP
A2: Calendrier des temps forts 2027
A4: Temps fort | B4: Date | C4: Effet
A5: Ramadan | B5: vers 8 févr. au 9 mars 2027 (estimé) | C5: Épargne, transferts
A6: Fête de fin du Ramadan | B6: vers 9-10 mars 2027 | C6: Dépenses des ménages
A7: Tabaski | B7: vers 16-17 mai 2027 | C7: Crédit à la consommation
A8: Fête de l’indépendance | B8: 7 août 2027 | C8: Diaspora
A9: Rentrée scolaire | B9: septembre 2027 (à vérifier) | C9: Crédit scolaire
A10: Fin d’année | B10: décembre 2027 | C10: Cartes, paiements
