Workbook

Sheet Calendrier novembre
C1: Calendrier éditorial, novembre 2026
C2: Instagram, Facebook, LinkedIn, stories et newsletter · Fil rouge du mois : santé des hommes (Movember) et prévention
C3: Rien ne part sans validation : chaque post passe de « À valider » à « Validé » avant programmation.
A5: Date | B5: Jour | C5: Heure | D5: Canal | E5: Format | F5: Pilier | G5: Cible | H5: Sujet | I5: Accroche A | J5: Accroche B (à tester) | K5: Légende | L5: Hashtags (Instagram, LinkedIn) | M5: Hashtags Facebook | N5: Appel à l'action | O5: Intention | P5: À fournir par l'équipe | Q5: Validation par | R5: Statut
A6: 2026-11-01 | B6: Dim | C6: 10:00 | D6: Stories Instagram + Facebook, statut WhatsApp | E6: Story fixe 9:16 | F6: Temps fort (sobre) | G6: Communauté | H6: Toussaint : pensée pour les familles | I6: Une pensée pour celles et ceux qui nous ont quittés. | K6: En ce jour de Toussaint, toute l'équipe de La Ruche Health a une pensée pour les familles et pour celles et ceux qui nous ont quittés. | N6: Aucun | O6: — | P6: Visuel sobre aux couleurs de la marque, sans produit ni lien | Q6: Direction | R6: À valider
A7: 2026-11-03 | B7: Mar | C7: 13:00 | D7: Instagram + Facebook | E7: Carrousel 4:5 (5 vues) | F7: Campagne santé du mois | G7: Hommes 25-55 ans et leurs proches | H7: Lancement de Movember : novembre, on parle santé des hommes | I7: Messieurs, à quand remonte votre dernier bilan ? | J7: Novembre, le mois où les hommes ont le droit de parler de leur santé. | K7: Messieurs, à quand remonte votre dernier bilan ? Novembre, c'est Movember : le mois où l'on parle santé masculine, sans gêne et sans tabou. Prostate, troubles urinaires, fertilité, stress, cœur : beaucoup d'hommes attendent d'avoir mal pour consulter. Tout le mois, nos spécialistes répondent à vos questions : - Urologue - Médecin généraliste - Nutritionniste - Psychologue Vous pouvez aussi poser votre question à Kiko sur WhatsApp, en toute discrétion. 📲 Téléchargez La Ruche Health et prenez rendez-vous. 🔗 Lien en bio. | L7: #LaRucheHealth #Téléconsultation #SantéDigitale #Santé #Prévention #SantéPourTous #AccèsAuxSoins #CotedIvoire #Movember #SantéMasculine #SantéDesHommes #Urologie | M7: #LaRucheHealth #Movember #SantéMasculine | N7: Prendre rendez-vous (lien en bio) | O7: TOFU | P7: 5 vues du carrousel (photo d'un homme ivoirien 35-50 ans), spécialités réellement disponibles en novembre | Q7: Médecin référent | R7: À valider
A8: 2026-11-03 | B8: Mar | C8: 09:00 | D8: LinkedIn | E8: Post texte + 1 image | F8: Kiko et la donnée santé | G8: Partenaires, bailleurs, médecins | H8: Ce que les hommes demandent à Kiko (et ce qu'ils n'osent pas demander en cabinet) | I8: Les hommes consultent peu. Mais ils écrivent à Kiko. | J8: Movember commence. Nos données disent quelque chose que les cabinets ne voient pas. | K8: Les hommes consultent peu. Mais ils écrivent à Kiko. Plus de 300 000 questions de santé ont déjà reçu une réponse de Kiko, souvent posées tard le soir, en privé. Ce que nos données montrent sur la santé masculine : ⟦3 enseignements anonymisés à fournir par l'équipe produit⟧. Ce mois-ci, nous ouvrons la conversation avec nos urologues, généralistes et psychologues. Parce qu'un homme qui pose la question en privé est un homme qu'on peut orienter vers le bon spécialiste. #Movember #SantéDigitale #HealthTech | L8: #Movember #SantéDigitale #HealthTech | N8: Commenter, partager | O8: TOFU | P8: 3 chiffres anonymisés issus de Kiko (questions des hommes, sujets, heures) | Q8: Direction + produit | R8: À valider
A9: 2026-11-04 | B9: Mer | C9: 12:00 | D9: Instagram + Facebook + LinkedIn | E9: Vidéo verticale 9:16, 60-75 s | F9: La Ruche Pro (médecins) | G9: Médecins et spécialistes | H9: L'Ordonnance du Dr Allé, épisode 6 : vos paiements et vos revenus sur La Ruche Pro | I9: Le patient a payé. Et vous, quand êtes-vous payé ? | J9: Épisode 6 : on parle argent, sans détour. | K9: L'Ordonnance du Dr Allé, épisode 6 Le patient a réservé, il a payé. Et vous, quand êtes-vous payé ? Dans ce nouvel épisode, Dr Allé vous montre comment suivre vos consultations et vos revenus depuis La Ruche Pro. Vous êtes professionnel de santé ? Rejoignez le réseau La Ruche Health. 🔗 Lien en bio. | L9: #LaRucheHealth #Téléconsultation #SantéDigitale #Santé #Prévention #SantéPourTous #AccèsAuxSoins #CotedIvoire #LaRuchePro #Médecins #eSanté | M9: #LaRucheHealth #LaRuchePro #Médecins | N9: Rejoindre le réseau (formulaire) | O9: MOFU | P9: Tournage de l'épisode 6 (sujet à confirmer par l'équipe) | Q9: Équipe produit | R9: À valider
A10: 2026-11-05 | B10: Jeu | C10: 13:00 | D10: Instagram + Facebook | E10: Vidéo verticale 9:16, 60-90 s (Reel) | F10: Éducation avec un spécialiste | G10: Hommes 35-60 ans, leurs épouses et enfants | H10: Un urologue répond : la prostate, à quel âge on en parle ? | I10: La prostate, à quel âge faut-il en parler à son médecin ? | J10: Uriner souvent la nuit, c'est l'âge… ou pas ? | K10: La prostate, à quel âge faut-il en parler à son médecin ? Uriner souvent la nuit, avoir du mal à vider sa vessie : beaucoup d'hommes pensent que « c'est l'âge ». Dr ⟦nom⟧, urologue sur La Ruche Health, vous explique quand consulter et comment se passe un premier rendez-vous. Une question ? Posez-la en commentaire, Dr ⟦nom⟧ y répondra. 📲 Téléchargez La Ruche Health et prenez rendez-vous. 🔗 Lien en bio. | L10: #LaRucheHealth #Téléconsultation #SantéDigitale #Santé #Prévention #SantéPourTous #AccèsAuxSoins #CotedIvoire #Movember #SantéMasculine #Prostate #Urologie | M10: #LaRucheHealth #Movember #Prostate | N10: Commenter / prendre rendez-vous | O10: TOFU | P10: Tournage avec un urologue du réseau, sous-titres | Q10: Urologue (contenu médical) | R10: À valider
A11: 2026-11-07 | B11: Sam | C11: 13:00 | D11: Instagram + Facebook | E11: Image 4:5 | F11: Médecin de la semaine | G11: Patients | H11: Médecin de la semaine : un urologue du réseau | I11: Médecin de la semaine | Dr ⟦nom⟧, urologue | K11: Médecin de la semaine | Dr ⟦nom⟧ Cette semaine, découvrez Dr ⟦nom⟧, urologue, ⟦années⟧ ans d'expérience. Il vous accompagne pour ⟦3 motifs de consultation⟧, en téléconsultation ou ⟦au cabinet / à domicile⟧. Prenez rendez-vous avec Dr ⟦nom⟧ sur La Ruche Health. 🔗 Lien en bio. | L11: #LaRucheHealth #Téléconsultation #SantéDigitale #Santé #Prévention #SantéPourTous #AccèsAuxSoins #CotedIvoire #MédecinDeLaSemaine #Urologie #Movember | M11: #LaRucheHealth #MédecinDeLaSemaine | N11: Prendre rendez-vous | O11: BOFU | P11: Photo, fiche et accord du médecin | Q11: Médecin concerné | R11: À valider
A12: 2026-11-10 | B12: Mar | C12: 13:00 | D12: Instagram + Facebook | E12: Carrousel 4:5 (4 vues) | F12: Kiko et l'application | G12: Jeunes 18-35 ans | H12: Une question gênante ? Kiko répond sur WhatsApp, à toute heure | I12: Il est 23 h et vous avez une question que vous n'osez poser à personne ? | J12: La question que vous n'osez pas poser, posez-la à Kiko. | K12: Il est 23 h et vous avez une question que vous n'osez poser à personne ? Kiko, l'assistant santé de La Ruche Health, vous répond sur WhatsApp, par écrit, par note vocale ou en photo. Et si votre situation le demande, Kiko vous oriente vers le bon spécialiste. Kiko ne remplace pas votre médecin : il vous aide à faire le premier pas. 💬 Écrivez à Kiko sur WhatsApp : +225 05 00 95 57 97 | L12: #LaRucheHealth #Téléconsultation #SantéDigitale #Santé #Prévention #SantéPourTous #AccèsAuxSoins #CotedIvoire #Kiko #DemandeÀKiko #SantéSexuelle #SantéMentale | M12: #LaRucheHealth #Kiko | N12: Écrire à Kiko sur WhatsApp | O12: MOFU | P12: Captures d'écran d'une conversation type (anonymisée) | Q12: Direction | R12: À valider
A13: 2026-11-10 | B13: Mar | C13: 09:00 | D13: LinkedIn | E13: Post texte + visuel | F13: La Ruche Pro (médecins) | G13: Spécialistes non encore inscrits | H13: Rejoindre le réseau : ce que La Ruche Pro change dans une semaine de consultation | I13: Être un excellent médecin ne suffit pas. Encore faut-il qu'on vous trouve. | K13: Être un excellent médecin ne suffit pas. Encore faut-il que vos patients vous trouvent. Sur La Ruche Health, un spécialiste dispose d'un profil, d'un lien de réservation, du paiement intégré, de la téléconsultation et du dossier patient numérique. Kiko, notre assistant, oriente vers vous les patients qui ont besoin de votre spécialité. Nous recherchons ce mois-ci des ⟦spécialités recherchées⟧. 👉 Rejoignez le réseau : ⟦lien du formulaire⟧ #eSanté #Télémédecine #CôtedIvoire | L13: #eSanté #Télémédecine #CôtedIvoire | N13: Remplir le formulaire d'inscription | O13: BOFU | P13: Spécialités prioritaires à recruter | Q13: Direction | R13: À valider
A14: 2026-11-12 | B14: Jeu | C14: 13:00 | D14: Instagram + Facebook | E14: Vidéo verticale 9:16, 60-75 s | F14: Éducation avec un spécialiste | G14: Adultes 30-60 ans | H14: Diabète : les signes qui doivent faire consulter (nutritionniste ou généraliste) | I14: Soif, fatigue, envie fréquente d'uriner : et si c'était votre glycémie ? | K14: Soif permanente, fatigue, envie fréquente d'uriner : et si c'était votre glycémie ? À l'approche de la Journée mondiale du diabète, Dr ⟦nom⟧, ⟦nutritionniste / médecin généraliste⟧ sur La Ruche Health, explique quels signes doivent vous faire consulter et quel examen demander. Ne restez pas dans le doute : un dépistage commence par une consultation. 📲 Téléchargez La Ruche Health et prenez rendez-vous. 🔗 Lien en bio. | L14: #LaRucheHealth #Téléconsultation #SantéDigitale #Santé #Prévention #SantéPourTous #AccèsAuxSoins #CotedIvoire #Diabète #JournéeMondialeDuDiabète #Nutrition | M14: #LaRucheHealth #Diabète | N14: Prendre rendez-vous | O14: TOFU | P14: Tournage avec le spécialiste, sous-titres | Q14: Spécialiste (contenu médical) | R14: À valider
A15: 2026-11-12 | B15: Jeu | C15: 09:00 | D15: LinkedIn | E15: Post texte (prise de parole du CEO) | F15: Leadership et vision | G15: Partenaires, bailleurs, institutions | H15: Maladies chroniques : ce que la téléconsultation change dans le suivi | I15: Le diabète ne se soigne pas en une consultation. Il se suit. | K15: Le diabète ne se soigne pas en une consultation. Il se suit. À deux jours de la Journée mondiale du diabète, une conviction : pour les maladies chroniques, le plus difficile n'est pas le premier rendez-vous, c'est le cinquième. Rappels, résultats d'analyses à domicile, renouvellement : c'est là que le numérique aide le patient à rester suivi. ⟦exemple concret ou chiffre à fournir par la direction⟧ #Diabète #SantéDigitale #MaladiesChroniques | L15: #Diabète #SantéDigitale #MaladiesChroniques | N15: Commenter | O15: TOFU | P15: Relecture et exemple par Rory Assandey (publication sur son profil ou la page) | Q15: Direction | R15: À valider
A16: 2026-11-14 | B16: Sam | C16: 13:00 | D16: Instagram + Facebook | E16: Carrousel 4:5 (4 vues) + médecin de la semaine | F16: Temps fort santé + Médecin de la semaine | G16: Adultes 30-60 ans | H16: Journée mondiale du diabète (14 novembre) + médecin de la semaine : un nutritionniste | I16: 14 novembre, Journée mondiale du diabète. | K16: 14 novembre | Journée mondiale du diabète Alimentation, activité physique, suivi régulier : le diabète se prévient et se gère, à condition d'être accompagné. Cette semaine, découvrez Dr ⟦nom⟧, ⟦nutritionniste⟧ : ⟦2 lignes de présentation⟧. Consultez-le en téléconsultation, et faites vos analyses à domicile avec nos partenaires. 📲 Téléchargez La Ruche Health et prenez rendez-vous. 🔗 Lien en bio. | L16: #LaRucheHealth #Téléconsultation #SantéDigitale #Santé #Prévention #SantéPourTous #AccèsAuxSoins #CotedIvoire #JournéeMondialeDuDiabète #Diabète #Nutrition #MédecinDeLaSemaine | M16: #LaRucheHealth #Diabète | N16: Prendre rendez-vous | O16: BOFU | P16: Photo et accord du nutritionniste mis en avant | Q16: Spécialiste | R16: À valider
A17: 2026-11-15 | B17: Dim | C17: 10:00 | D17: Stories Instagram + Facebook, statut WhatsApp | E17: Story fixe 9:16 | F17: Temps fort (sobre) | G17: Communauté | H17: Journée nationale de la Paix | I17: 15 novembre, Journée nationale de la Paix. | K17: 15 novembre, Journée nationale de la Paix. Prendre soin les uns des autres, c'est aussi ça, la paix. Bonne journée à toutes et à tous. | N17: Aucun | O17: — | P17: Visuel sobre, sans produit | Q17: Direction | R17: À valider
A18: 2026-11-17 | B18: Mar | C18: 13:00 | D18: Instagram + Facebook | E18: Carrousel 4:5 (5 vues) | F18: Temps fort santé (santé des femmes) | G18: Femmes 20-50 ans | H18: Journée mondiale pour l'élimination du cancer du col de l'utérus : frottis et HPV | I18: Après Octobre Rose, parlons d'un autre cancer qu'on peut éviter. | J18: Frottis, HPV : ce que toute femme devrait savoir. | K18: Après Octobre Rose, parlons d'un autre cancer qui se dépiste : le cancer du col de l'utérus. 17 novembre, Journée mondiale pour son élimination. Frottis, test HPV, vaccination : nos gynécologues et sages-femmes vous expliquent ce qu'il faut savoir, et à quel âge. Vous pouvez consulter : - Gynécologue - Sage-femme Parce que votre santé ne doit pas attendre. 📲 Téléchargez La Ruche Health et prenez rendez-vous. 🔗 Lien en bio. | L18: #LaRucheHealth #Téléconsultation #SantéDigitale #Santé #Prévention #SantéPourTous #AccèsAuxSoins #CotedIvoire #SantéDesFemmes #CancerDuColDeLUtérus #HPV #Dépistage #Gynécologie | M18: #LaRucheHealth #SantéDesFemmes #Dépistage | N18: Prendre rendez-vous | O18: TOFU | P18: Contenu des 5 vues (âges de dépistage) | Q18: Gynécologue (contenu médical) | R18: À valider
A19: 2026-11-17 | B19: Mar | C19: 09:00 | D19: LinkedIn | E19: Post texte + visuel | F19: Santé des femmes | G19: Partenaires, ONG, institutions | H19: Cancer du col : pourquoi la conversation privée est la première étape du dépistage | I19: Ce que nous a appris Octobre Rose : les femmes posent leurs questions la nuit, en privé. | K19: 17 novembre, Journée mondiale pour l'élimination du cancer du col de l'utérus. Selon nos données, 41 % des femmes qui nous écrivent se préoccupent de leur santé reproductive. La première étape d'un dépistage, c'est souvent une question posée en privé, puis un rendez-vous avec une gynécologue ou une sage-femme. C'est ce parcours que nous construisons : de la question au soin. #SantéDesFemmes #Dépistage #SantéDigitale | L19: #SantéDesFemmes #Dépistage #SantéDigitale | N19: Partager | O19: TOFU | P19: Vérifier que le chiffre de 41 % (site laruche.health) est toujours à jour | Q19: Direction | R19: À valider
A20: 2026-11-18 | B20: Mer | C20: 12:00 | D20: Instagram + Facebook + LinkedIn | E20: Vidéo verticale 9:16, 60-75 s | F20: La Ruche Pro (médecins) | G20: Médecins et spécialistes | H20: L'Ordonnance du Dr Allé, épisode 7 : ⟦sujet à choisir : avis patients, suivi après consultation…⟧ | I20: Épisode 7 : et après la consultation ? | K20: L'Ordonnance du Dr Allé, épisode 7 ⟦Accroche selon le sujet retenu⟧ Dans ce nouvel épisode, Dr Allé vous montre ⟦sujet⟧ sur La Ruche Pro. Vous êtes professionnel de santé ? Rejoignez le réseau La Ruche Health. 🔗 Lien en bio. | L20: #LaRucheHealth #Téléconsultation #SantéDigitale #Santé #Prévention #SantéPourTous #AccèsAuxSoins #CotedIvoire #LaRuchePro #Médecins #eSanté | M20: #LaRucheHealth #LaRuchePro | N20: Rejoindre le réseau | O20: MOFU | P20: Sujet et tournage de l'épisode 7 | Q20: Équipe produit | R20: À valider
A21: 2026-11-19 | B21: Jeu | C21: 13:00 | D21: Instagram + Facebook | E21: Vidéo verticale 9:16, 45-60 s | F21: Éducation avec un spécialiste | G21: Grand public | H21: Semaine mondiale du bon usage des antimicrobiens (18-24 nov.) : un antibiotique contre la grippe ? | I21: Un antibiotique pour soigner la grippe ? Mauvaise idée. | K21: Un antibiotique pour soigner la grippe ou un rhume ? Mauvaise idée. C'est la Semaine mondiale de sensibilisation à la résistance aux antimicrobiens (18-24 novembre). Dr ⟦nom⟧, ⟦pharmacienne / médecin généraliste⟧ sur La Ruche Health, explique pourquoi on ne prend pas d'antibiotique sans ordonnance, et pourquoi on va jusqu'au bout du traitement. Un doute sur un traitement ? Demandez l'avis d'un professionnel. 📲 Téléchargez La Ruche Health et prenez rendez-vous. 🔗 Lien en bio. | L21: #LaRucheHealth #Téléconsultation #SantéDigitale #Santé #Prévention #SantéPourTous #AccèsAuxSoins #CotedIvoire #Antibiotiques #BonUsageDesAntibiotiques #Automédication | M21: #LaRucheHealth #Antibiotiques | N21: Prendre rendez-vous | O21: TOFU | P21: Tournage avec un pharmacien ou un généraliste | Q21: Spécialiste (contenu médical) | R21: À valider
A22: 2026-11-21 | B22: Sam | C22: 13:00 | D22: Instagram + Facebook | E22: Image 4:5 | F22: Médecin de la semaine | G22: Patients | H22: Médecin de la semaine : un médecin généraliste | I22: Médecin de la semaine | Dr ⟦nom⟧, médecin généraliste | K22: Médecin de la semaine | Dr ⟦nom⟧ Cette semaine, découvrez Dr ⟦nom⟧, médecin généraliste, ⟦années⟧ ans d'expérience. Votre premier point de contact pour ⟦3 motifs de consultation⟧, en téléconsultation ou à domicile. Prenez rendez-vous avec Dr ⟦nom⟧ sur La Ruche Health. 🔗 Lien en bio. | L22: #LaRucheHealth #Téléconsultation #SantéDigitale #Santé #Prévention #SantéPourTous #AccèsAuxSoins #CotedIvoire #MédecinDeLaSemaine #MédecinGénéraliste | M22: #LaRucheHealth #MédecinDeLaSemaine | N22: Prendre rendez-vous | O22: BOFU | P22: Photo, fiche et accord du médecin | Q22: Médecin concerné | R22: À valider
A23: 2026-11-24 | B23: Mar | C23: 13:00 | D23: Instagram + Facebook | E23: Carrousel 4:5 (6 vues) | F23: Kiko et l'application | G23: Nouveaux utilisateurs | H23: Votre première téléconsultation, étape par étape | I23: Première téléconsultation ? Voici comment ça se passe, en 5 étapes. | K23: Première téléconsultation ? Voici comment ça se passe, en 5 étapes. 1. Choisissez votre spécialiste sur l'application ou le site. 2. Réservez le créneau qui vous convient. 3. Payez en ligne. 4. Échangez avec le médecin en vidéo, à l'heure prévue. 5. Retrouvez votre compte rendu dans l'application. Plus de 2 300 consultations en dermatologie, 1 500 avec nos généralistes et 1 000 avec nos sages-femmes ont déjà été réservées sur La Ruche Health. 📲 Téléchargez La Ruche Health et prenez rendez-vous. 🔗 Lien en bio. | L23: #LaRucheHealth #Téléconsultation #SantéDigitale #Santé #Prévention #SantéPourTous #AccèsAuxSoins #CotedIvoire #PremièreConsultation #Kiko | M23: #LaRucheHealth #Téléconsultation | N23: Télécharger l'application | O23: BOFU | P23: Captures de l'application à jour (iOS et Android), moyens de paiement acceptés | Q23: Équipe produit | R23: À valider
A24: 2026-11-24 | B24: Mar | C24: 09:00 | D24: LinkedIn | E24: Post texte (prise de parole du CEO) | F24: Leadership et vision | G24: Partenaires, investisseurs, médecins | H24: De la question au soin : pourquoi un chatbot qui répond ne suffit pas | I24: Un patient écrit à un cabinet. Le vrai travail commence à ce moment-là. | K24: Un patient écrit : un symptôme, une question, une envie de rendez-vous. Le vrai travail commence à ce moment-là. Quel spécialiste ? Quelle information manque ? Combien coûte la consultation ? Qui est disponible ? Le paiement passe-t-il ? Le patient viendra-t-il ? Chez La Ruche Health, nous construisons ce parcours complet : accueil, orientation, réservation, paiement, rappel, suivi. ⟦exemple réel d'un parcours patient, anonymisé, à fournir⟧ #SantéDigitale #IA #HealthTech | L24: #SantéDigitale #IA #HealthTech | N24: Commenter | O24: MOFU | P24: Exemple réel anonymisé + relecture par Rory Assandey | Q24: Direction | R24: À valider
A25: 2026-11-25 | B25: Mer | C25: 10:00 | D25: Instagram + Facebook | E25: Image 4:5 sobre | F25: Temps fort (sujet sensible) | G25: Femmes | H25: Journée internationale pour l'élimination de la violence à l'égard des femmes | I25: Vous n'êtes pas seule. | K25: 25 novembre | Journée internationale pour l'élimination de la violence à l'égard des femmes. Vous n'êtes pas seule. Parler à un professionnel est un premier pas. Nos psychologues vous écoutent, en toute confidentialité. En cas d'urgence : ⟦numéro d'écoute ou d'urgence en Côte d'Ivoire à vérifier⟧. | L25: #LaRucheHealth #Stopviolences #SantéDesFemmes #SantéMentale | M25: #LaRucheHealth #SantéDesFemmes | N25: Contacter un psychologue | O25: — | P25: Numéro d'écoute officiel vérifié ; psychologues disponibles | Q25: Direction (sujet sensible) | R25: À valider
A26: 2026-11-26 | B26: Jeu | C26: 13:00 | D26: Instagram + Facebook | E26: Vidéo verticale 9:16, 60-90 s | F26: Éducation avec un spécialiste | G26: Hommes 20-45 ans | H26: Movember : la santé mentale des hommes, avec un psychologue | I26: « Un homme, ça ne se plaint pas. » Et si c'était ça, le problème ? | K26: « Un homme, ça ne se plaint pas. » Et si c'était ça, le problème ? Stress, fatigue, irritabilité, sommeil qui se dérègle : chez les hommes, l'épuisement se cache souvent. Dr ⟦nom⟧, psychologue sur La Ruche Health, explique comment le repérer et quand en parler. En parler, c'est déjà se soigner. 📲 Téléchargez La Ruche Health et prenez rendez-vous. 🔗 Lien en bio. | L26: #LaRucheHealth #Téléconsultation #SantéDigitale #Santé #Prévention #SantéPourTous #AccèsAuxSoins #CotedIvoire #Movember #SantéMentale #SantéMasculine #Psychologie | M26: #LaRucheHealth #Movember #SantéMentale | N26: Prendre rendez-vous | O26: TOFU | P26: Tournage avec un psychologue | Q26: Psychologue (contenu médical) | R26: À valider
A27: 2026-11-26 | B27: Jeu | C27: 09:00 | D27: LinkedIn | E27: Post + infographie | F27: Preuve et résultats | G27: Partenaires, médecins | H27: Ce que les patients réservent le plus sur La Ruche Health | I27: Dermatologie, médecine générale, sages-femmes : le podium de nos réservations. | K27: Dermatologie, médecine générale, sages-femmes : le podium de nos réservations. Plus de 2 300 consultations en dermatologie, 1 500 avec nos généralistes, 1 000 avec nos sages-femmes. Derrière ces chiffres, des patients qui ont trouvé un spécialiste sans salle d'attente, et des médecins qui ont trouvé de nouveaux patients. Merci à tous les professionnels qui font La Ruche Health. #SantéDigitale #Télémédecine #CôtedIvoire | L27: #SantéDigitale #Télémédecine #CôtedIvoire | N27: Partager | O27: MOFU | P27: Confirmer que les chiffres du site sont à jour | Q27: Direction | R27: À valider
A28: 2026-11-27 | B28: Ven | C28: 10:00 | D28: Newsletter (e-mail) | E28: Newsletter | F28: Synthèse du mois | G28: Abonnés à la newsletter | H28: Newsletter de novembre : santé des hommes, diabète, dépistage du col | I28: Novembre chez La Ruche Health : ce qu'il faut retenir | K28: Au sommaire : les conseils de nos urologues et psychologues pour Movember, les signes du diabète, le dépistage du cancer du col de l'utérus, et les médecins du mois à consulter. | N28: Prendre rendez-vous | O28: MOFU | P28: Outil d'envoi de la newsletter et liste des abonnés (rythme d'envoi à confirmer) | Q28: Direction | R28: À valider
A29: 2026-11-28 | B29: Sam | C29: 13:00 | D29: Instagram + Facebook | E29: Image 4:5 | F29: Médecin de la semaine | G29: Patients | H29: Médecin de la semaine : un psychologue ou une gynécologue | I29: Médecin de la semaine | Dr ⟦nom⟧ | K29: Médecin de la semaine | Dr ⟦nom⟧ Cette semaine, découvrez Dr ⟦nom⟧, ⟦spécialité⟧, ⟦années⟧ ans d'expérience. Elle ou il vous accompagne pour ⟦3 motifs de consultation⟧. Prenez rendez-vous avec Dr ⟦nom⟧ sur La Ruche Health. 🔗 Lien en bio. | L29: #LaRucheHealth #Téléconsultation #SantéDigitale #Santé #Prévention #SantéPourTous #AccèsAuxSoins #CotedIvoire #MédecinDeLaSemaine | M29: #LaRucheHealth #MédecinDeLaSemaine | N29: Prendre rendez-vous | O29: BOFU | P29: Photo, fiche et accord du médecin | Q29: Médecin concerné | R29: À valider
A30: 2026-11-30 | B30: Lun | C30: 13:00 | D30: Instagram + Facebook | E30: Carrousel 4:5 (4 vues) | F30: Temps fort santé | G30: Jeunes 18-35 ans | H30: Avant le 1er décembre (Journée mondiale du sida) : le dépistage du VIH, simple et confidentiel | I30: Le dépistage du VIH, vous en parlez quand ? | K30: Le dépistage du VIH, vous en parlez quand ? Demain, 1er décembre, c'est la Journée mondiale de lutte contre le sida. Se faire dépister, c'est simple, rapide et confidentiel. Nos médecins et sages-femmes vous expliquent comment, et vous orientent. Une question ? Kiko vous répond en privé sur WhatsApp : +225 05 00 95 57 97 📲 Téléchargez La Ruche Health et prenez rendez-vous. 🔗 Lien en bio. | L30: #LaRucheHealth #Téléconsultation #SantéDigitale #Santé #Prévention #SantéPourTous #AccèsAuxSoins #CotedIvoire #JournéeMondialeDuSida #Dépistage #SantéSexuelle #IST | M30: #LaRucheHealth #Dépistage #SantéSexuelle | N30: Écrire à Kiko / prendre rendez-vous | O30: TOFU | P30: Lieux ou modalités de dépistage proposés (à domicile ?) | Q30: Médecin référent | R30: À valider

Sheet Répartition
A1: Répartition du mois (se calcule seule)
A3: Pilier | B3: Nombre de posts
A4: Campagne santé | B4: =COUNTIF('Calendrier novembre'!F6:F30,"*Campagne santé*")
A5: Éducation avec un spécialiste | B5: =COUNTIF('Calendrier novembre'!F6:F30,"*Éducation avec un spécialiste*")
A6: Médecin de la semaine | B6: =COUNTIF('Calendrier novembre'!F6:F30,"*Médecin de la semaine*")
A7: Kiko | B7: =COUNTIF('Calendrier novembre'!F6:F30,"*Kiko*")
A8: La Ruche Pro | B8: =COUNTIF('Calendrier novembre'!F6:F30,"*La Ruche Pro*")
A9: Temps fort | B9: =COUNTIF('Calendrier novembre'!F6:F30,"*Temps fort*")
A10: Leadership | B10: =COUNTIF('Calendrier novembre'!F6:F30,"*Leadership*")
A11: Preuve | B11: =COUNTIF('Calendrier novembre'!F6:F30,"*Preuve*")
A12: Synthèse | B12: =COUNTIF('Calendrier novembre'!F6:F30,"*Synthèse*")
A14: Canal | B14: Nombre de posts
A15: Instagram | B15: =COUNTIF('Calendrier novembre'!D6:D30,"*Instagram*")
A16: Facebook | B16: =COUNTIF('Calendrier novembre'!D6:D30,"*Facebook*")
A17: LinkedIn | B17: =COUNTIF('Calendrier novembre'!D6:D30,"*LinkedIn*")
A18: Stories | B18: =COUNTIF('Calendrier novembre'!D6:D30,"*Stories*")
A19: Newsletter | B19: =COUNTIF('Calendrier novembre'!D6:D30,"*Newsletter*")
A21: Intention | B21: Nombre de posts
A22: TOFU | B22: =COUNTIF('Calendrier novembre'!O6:O30,"*TOFU*")
A23: MOFU | B23: =COUNTIF('Calendrier novembre'!O6:O30,"*MOFU*")
A24: BOFU | B24: =COUNTIF('Calendrier novembre'!O6:O30,"*BOFU*")
A26: Statut | B26: Nombre de posts
A27: À valider | B27: =COUNTIF('Calendrier novembre'!R6:R30,"*À valider*")
A28: Validé | B28: =COUNTIF('Calendrier novembre'!R6:R30,"*Validé*")
A29: Programmé | B29: =COUNTIF('Calendrier novembre'!R6:R30,"*Programmé*")
A30: Publié | B30: =COUNTIF('Calendrier novembre'!R6:R30,"*Publié*")
A32: Les comptes se recoupent : un post Instagram + Facebook compte dans les deux canaux, et le 14 novembre compte en temps fort et en médecin de la semaine.

Sheet Temps forts
A1: Temps forts de novembre 2026, avec leur source
A3: Date | B3: Temps fort | C3: Type | D3: Date sûre ? | E3: Source | F3: Lien
A4: Tout le mois | B4: Movember (santé masculine) | C4: Mois de sensibilisation | D4: Oui | E4: Santé Canada, calendrier des journées relatives à la santé | F4: https://www.canada.ca/fr/sante-canada/services/calendrier-journees-relatives-sante.html
A5: Dim. 1er nov. | B5: Toussaint (férié en Côte d'Ivoire) | C5: Fête fixe, recueillement : visuel sobre | D5: Oui | E5: Liste des fêtes à date fixe en Côte d'Ivoire
A6: Sam. 14 nov. | B6: Journée mondiale du diabète | C6: Journée OMS / ONU | D6: Oui | E6: OMS | F6: https://www.who.int/fr/campaigns/world-diabetes-day
A7: Dim. 15 nov. | B7: Journée nationale de la Paix (fériée) | C7: Fête fixe | D7: Oui | E7: Liste des fêtes à date fixe en Côte d'Ivoire
A8: Dim. 15 nov. | B8: Journée mondiale de la prématurité | C8: Journée OMS | D8: Oui | E8: OMS, campagnes mondiales | F8: https://www.who.int/campaigns/
A9: Mar. 17 nov. | B9: Journée mondiale pour l'élimination du cancer du col de l'utérus | C9: Journée OMS | D9: Oui | E9: OMS, campagnes mondiales | F9: https://www.who.int/campaigns/
A10: 18-24 nov. | B10: Semaine mondiale de sensibilisation à la résistance aux antimicrobiens | C10: Semaine OMS | D10: Oui | E10: ONU / OMS | F10: https://www.un.org/en/observances/world-antibiotic-awareness-week-13-19-november-who
A11: Mer. 25 nov. | B11: Journée internationale pour l'élimination de la violence à l'égard des femmes | C11: Journée ONU, sujet sensible | D11: Oui | E11: Santé Canada (rappel des journées ONU) | F11: https://www.canada.ca/fr/sante-canada/services/calendrier-journees-relatives-sante.html
A12: Mar. 1er déc. | B12: Journée mondiale de lutte contre le sida (post de veille le 30 nov.) | C12: Journée OMS | D12: Oui | E12: OMS, campagnes mondiales | F12: https://www.who.int/campaigns/
A13: — | B13: Fêtes musulmanes | C13: Aucune en novembre 2026 | D13: — | E13: Aucune date annoncée par le COSIM sur la période
A16: Non retenus faute de place ou de lien direct avec l'offre : Journée de la prématurité (15 nov., un dimanche férié), à garder si un pédiatre ou une sage-femme du réseau veut s'exprimer.

Sheet Relevé du compte
A1: Ce que montre votre compte Instagram (relevé du 20 octobre 2026)
A2: Échantillon : les 40 dernières publications visibles sur @laruchehealth, du 28 juillet au 20 octobre 2026 (39 de votre compte, 1 d'un partenaire).
A4: Mesure | B4: Constat
A5: Rythme | B5: 39 publications en 12 semaines, soit un peu plus de 3 par semaine
A6: Jours et heure | B6: Surtout le mardi (13 posts), le jeudi (10) et le samedi (7), le plus souvent vers 13 h
A7: Formats | B7: 17 images, 14 vidéos, 9 carrousels ; 34 publications sur 40 en vertical (4:5 ou 9:16)
A8: Durée des vidéos | B8: Médiane 75 s sur 14 vidéos (de 47 s à 5 min 21 s)
A9: Vues des vidéos | B9: Médiane 316 lectures sur vos 13 vidéos ; au-dessus de 2 800 : la santé intime avec Dr Kattié (3 035, avec Brut Africa) et « Tous les boutons ne sont pas de l'acné » avec Dr Lyndouce (2 830)
A10: Ce qui marche le mieux | B10: Un spécialiste qui répond face caméra à une question de santé intime, de peau ou d'homme. La santé masculine (745 lectures) fait plus de deux fois la médiane
A11: Ce qui marche moins | B11: Les images « Médecin de la semaine » : 6 j'aime en médiane sur 9 posts. Utiles pour la réservation, faibles en portée
A12: Série B2B | B12: « L'Ordonnance du Dr Allé », 5 vidéos (jusqu'à l'épisode 5), de 100 à 702 lectures : à garder pour les médecins, et à pousser sur LinkedIn
A13: Mots-dièse les plus employés | B13: #LaRucheHealth (37), #Téléconsultation (18), #SantéDigitale (13), #Santé (12), #MédecinDeLaSemaine (9)
A14: Exclu du calcul | B14: La vidéo « Derrière la Blouse » (27 238 vues) est la publication d'un partenaire qui vous cite, pas une publication de votre compte
A16: Non relevés : Facebook, LinkedIn et TikTok (pages non lisibles sans accès), et les statistiques de portée et de réservations, qui demandent l'accès aux comptes.

Sheet Mode d'emploi
A1: Mode d'emploi
A3: • Les marques ⟦…⟧ sont les informations que seule votre équipe peut donner : nom du médecin, chiffre interne, numéro d'écoute. Un post ne part pas tant qu'il en reste une.
A4: • Tout contenu médical (vidéo d'un spécialiste, conseil de dépistage) est relu par le médecin qui parle avant publication.
A5: • Les vidéos se tournent en vertical 9:16, entre 60 et 90 secondes, sous-titrées : c'est ce qui marche le mieux sur votre compte.
A6: • Premières lignes en gras (caractères gras Unicode), comme vos publications actuelles.
A7: • Les chiffres de consultations (2 300 en dermatologie, 1 500 en médecine générale, 1 000 sages-femmes) les 41 % et les 300 000 questions viennent de votre site laruche.health, relu le 20 octobre 2026 : à confirmer avant publication.
A8: • Statut : passez la colonne R à « Validé » quand un post est accepté ; il passe en vert. Rien n'est programmé sans cette validation.
A9: • Police : Montserrat par défaut, en attendant votre charte. Couleurs relevées sur votre logo : bleu nuit #0B0249, turquoise #4EC7C5.
