Workbook

Sheet Synthèse
C1: Origin7 · Plan média de janvier 2027 · 5 000 000 F CFA
C2: Version 1 du 20 octobre 2026, à valider par la direction.
B4: En bref
A5: Période | B5: 4 semaines, du lundi 11 janvier au dimanche 7 février 2027 : le moment où les entreprises ouvrent leurs budgets de l'année et choisissent leurs prestataires.
A6: Objectif | B6: 25 demandes de devis qualifiées, 12 rendez-vous et 4 contrats signés sous 60 jours.
A7: Cible | B7: Directions communication, marketing, ressources humaines et générales des entreprises de plus de 50 salariés à Abidjan, qui organisent lancements, salons et soirées.
A8: Message | B8: « Votre événement est prêt le jour J, même quand tout s'est décidé la veille. » La campagne « Au 7e jour » montre les coulisses réelles de vos délais courts.
A9: Le parti pris | B9: 70 % du budget sur des canaux où se trouvent les décideurs et où chaque franc se mesure : LinkedIn, Google, presse économique en ligne, coffrets livrés en main propre. Pas de radio, de télévision ni d'affichage : trop large pour une cible aussi précise.
A10: Le contrôle | B10: Point chaque lundi ; une annonce qui coûte plus de 150 000 F par demande qualifiée est coupée. La réserve de 500 000 F va le 25 janvier au canal qui marche le mieux.
A12: La répartition en un coup d'œil
A13: Poste | B13: Montant | C13: Part | D13: Indicateur
A14: ='Répartition'!A5 | B14: ='Répartition'!C5 | C14: ='Répartition'!D5 | D14: Demandes qualifiées
A15: ='Répartition'!A6 | B15: ='Répartition'!C6 | C15: ='Répartition'!D6 | D15: Messages et demandes
A16: ='Répartition'!A7 | B16: ='Répartition'!C7 | C16: ='Répartition'!D7 | D16: Demandes via le site
A17: ='Répartition'!A8 | B17: ='Répartition'!C8 | C17: ='Répartition'!D8 | D17: Visites du site
A18: ='Répartition'!A9 | B18: ='Répartition'!C9 | C18: ='Répartition'!D9 | D18: Rendez-vous
A19: ='Répartition'!A10 | B19: ='Répartition'!C10 | C19: ='Répartition'!D10 | D19: Contenus livrés
A20: ='Répartition'!A11 | B20: ='Répartition'!C11 | C20: ='Répartition'!D11 | D20: Coût par demande
A21: Total | B21: ='Répartition'!C12 | C21: ='Répartition'!C13
A23: Les onglets
A24: Répartition | B24: Le budget poste par poste, ce que chaque franc achète et sa règle de dépense
A25: Plan média | B25: Chaque support : cible, format, message, période, budget, objectif, responsable ; et les canaux sans achat
A26: Calendrier | B26: La dépense semaine par semaine et les rendez-vous du mois
A27: Estimations | B27: Ce que le budget peut produire, avec des hypothèses modifiables
A28: Pilotage et risques | B28: Les indicateurs du lundi, les risques et les décisions à prendre

Sheet Répartition
C1: Répartition du budget : 5 000 000 F CFA sur un mois
C2: Du lundi 11 janvier au dimanche 7 février 2027. Montants en F CFA, toutes taxes comprises.
A4: Poste | B4: Famille | C4: Montant | D4: Part | E4: Ce que ça achète | F4: Règle de dépense
A5: Publicité LinkedIn | B5: Publicité en ligne | C5: 1600000 | D5: =C5/$C$12 | E5: Vidéos « Au 7e jour » et formulaire de demande de devis intégré, auprès des directions communication, marketing, RH et générales d'Abidjan | F5: Plafond quotidien fixé dans la régie ; arrêt d'une annonce au-delà de 150 000 F par demande qualifiée
A6: Publicité Facebook et Instagram | B6: Publicité en ligne | C6: 600000 | D6: =C6/$C$12 | E6: Diffusion des vidéos et carrousels, puis relance des personnes qui ont vu les vidéos ou visité le site | F6: Plafond quotidien ; 70 % en relance des personnes déjà touchées dès la 2e semaine
A7: Publicité Google (recherche) | B7: Publicité en ligne | C7: 500000 | D7: =C7/$C$12 | E7: Annonces sur les recherches « agence événementielle Abidjan », « organisation soirée entreprise », « stand salon Abidjan » | F7: Enchères plafonnées ; mots-clés sans demande coupés au bout de 7 jours
A8: Presse économique en ligne | B8: Presse et relations médias | C8: 700000 | D8: =C8/$C$12 | E8: 2 articles sponsorisés (une étude de cas, une tribune sur les délais courts) et 1 insertion dans une lettre d'information économique | F8: Paiement à la publication, sur devis signé ; textes validés par la direction
A9: Coffrets « Au 7e jour » aux décideurs | B9: Marketing direct | C9: 400000 | D9: =C9/$C$12 | E9: 40 coffrets livrés en main propre aux décideurs prioritaires : carte manuscrite, objet de marque, QR code vers la prise de rendez-vous | F9: Liste des 40 décideurs validée par la direction avant commande
A10: Production des contenus | B10: Production | C10: 700000 | D10: =C10/$C$12 | E10: 4 vidéos courtes tournées sur des événements réels, 15 déclinaisons de visuels publicitaires, photos d'équipe | F10: Paiement sur livraison des fichiers ; droits d'usage accordés par écrit par les clients filmés
A11: Réserve | B11: Réserve | C11: 500000 | D11: =C11/$C$12 | E11: Débloquée le lundi 25 janvier sur le canal qui produit les demandes qualifiées les moins chères | F11: Aucun engagement sans accord écrit de la direction
A12: Total | C12: =SUM(C5:C11) | D12: =C12/5000000
A13: Contrôle | C13: =IF(C12=5000000,"Budget respecté","Écart au budget")
A15: Par grande famille
A16: Famille | C16: Montant | D16: Part
A17: Publicité en ligne | C17: =SUMIF($B$5:$B$11,A17,$C$5:$C$11) | D17: =C17/$C$12
A18: Presse et relations médias | C18: =SUMIF($B$5:$B$11,A18,$C$5:$C$11) | D18: =C18/$C$12
A19: Marketing direct | C19: =SUMIF($B$5:$B$11,A19,$C$5:$C$11) | D19: =C19/$C$12
A20: Production | C20: =SUMIF($B$5:$B$11,A20,$C$5:$C$11) | D20: =C20/$C$12
A21: Réserve | C21: =SUMIF($B$5:$B$11,A21,$C$5:$C$11) | D21: =C21/$C$12
A23: Pourquoi cette répartition : vos clients sont des décideurs d'entreprise. Ils se trouvent sur LinkedIn, lisent la presse économique et recherchent un prestataire sur Google le jour où le besoin tombe. La radio, la télévision et l'affichage touchent surtout le grand public : avec 5 000 000 F, on y achèterait peu de passages, vus par peu de vos cibles.

Sheet Plan média
C1: Plan média détaillé, support par support
C2: Chaque ligne : à qui on parle, avec quoi, quand, pour combien, et ce qu'on en attend.
A4: Support | B4: Cible | C4: Format | D4: Message | E4: Période | F4: Budget | G4: Indicateur principal | H4: Objectif du mois | I4: Responsable
A5: Publicité LinkedIn | B5: Fonctions communication, marketing, RH, direction générale ; entreprises de plus de 50 salariés ; Abidjan. Exclusion : agences concurrentes | C5: Vidéo courte (30 s), carrousel « 7 erreurs », formulaire de devis intégré | D5: « Votre événement est prêt le jour J, même quand tout s'est décidé la veille. » | E5: 11 janv. → 7 févr. | F5: ='Répartition'!C5 | G5: Demandes de devis qualifiées | H5: 12 | I5: Responsable digital
A6: Publicité Facebook et Instagram | B6: Professionnels de la communication et de l'événementiel, Abidjan, 25-55 ans ; puis relance des personnes ayant vu 50 % d'une vidéo ou visité le site | C6: Reels 15-30 s, carrousels, stories | D6: Les coulisses de la veille du jour J | E6: 11 janv. → 7 févr. | F6: ='Répartition'!C6 | G6: Messages WhatsApp et demandes reçues | H6: 6 | I6: Responsable digital
A7: Publicité Google (recherche) | B7: Personnes qui cherchent une agence événementielle à Abidjan | C7: Annonces texte, renvoi vers une page « devis en 24 h » | D7: « Lancement, salon, soirée : devis sous 24 h. » | E7: 11 janv. → 7 févr. | F7: ='Répartition'!C7 | G7: Demandes de devis via le site | H7: 5 | I7: Responsable digital
A8: Presse économique en ligne | B8: Lecteurs décideurs de la presse économique ivoirienne | C8: 2 articles sponsorisés + 1 insertion en lettre d'information | D8: Étude de cas d'un événement livré en délai court ; tribune de la direction | E8: Articles semaines 2 et 3 ; lettre semaine 3 | F8: ='Répartition'!C8 | G8: Visites du site depuis les articles | H8: 400 visites | I8: Cheffe de projet
A9: Coffrets « Au 7e jour » | B9: 40 décideurs prioritaires : grands comptes visés, clients à réactiver | C9: Coffret livré au bureau, carte signée, QR code de prise de rendez-vous | D9: « Au 7e jour, votre événement est prêt. Parlons du prochain. » | E9: Livraison semaine 2, relance téléphonique semaine 3 | F9: ='Répartition'!C9 | G9: Rendez-vous obtenus | H9: 8 | I9: Cheffe de projet
A10: Production des contenus | B10: Tous les supports ci-dessus | C10: 4 vidéos, 15 visuels, photos d'équipe | D10: Montrer le travail réel, pas des images de banque | E10: Avant le 8 janvier | F10: ='Répartition'!C10 | G10: Contenus livrés à temps | H10: 100 % le 8 janvier | I10: Cheffe de projet
A11: Réserve | B11: Selon les résultats | C11: Renfort du meilleur canal | D11: Inchangé | E11: À partir du 25 janv. | F11: ='Répartition'!C11 | G11: Coût par demande qualifiée | H11: Le plus bas des canaux | I11: Direction
A13: Les canaux sans achat, qui tournent en parallèle
A14: Canal | B14: Ce qu'on y fait | C14: Rythme | I14: Responsable
A15: Page LinkedIn Origin7 et profils des dirigeants | B15: Publications de la série « Au 7e jour » ; les dirigeants partagent et commentent | C15: 3 par semaine | I15: Direction et chargé·e des réseaux
A16: Instagram Origin7 | B16: Coulisses, reels, stories pendant les événements | C16: 3 par semaine | I16: Chargé·e des réseaux sociaux
A17: WhatsApp Business | B17: Réponse aux demandes en moins de 2 heures ouvrées ; catalogue des prestations | C17: Tous les jours | I17: Chargé·e de clientèle
A18: Lettre d'information aux clients et prospects | B18: Vœux 2027 et dates libres du premier trimestre | C18: 1 envoi le 12 janvier, 1 relance le 2 février | I18: Cheffe de projet
A19: Prospection directe | B19: Appels de suivi des coffrets et des personnes qui ont ouvert la lettre | C19: 10 appels par jour ouvré | I19: Chargé·e de prospection

Sheet Calendrier
C1: Calendrier et rythme de dépense
C2: Montants prévus par semaine. Le total de chaque ligne doit égaler son budget.
A4: Poste | B4: Préparation (avant le 11 janv.) | C4: S1 · 11 au 17 janv. | D4: S2 · 18 au 24 janv. | E4: S3 · 25 au 31 janv. | F4: S4 · 1er au 7 févr. | G4: Total | H4: Contrôle
A5: Publicité LinkedIn | B5: 0 | C5: 400000 | D5: 400000 | E5: 400000 | F5: 400000 | G5: =SUM(B5:F5) | H5: =IF(G5='Répartition'!C5,"OK","À revoir")
A6: Publicité Facebook et Instagram | B6: 0 | C6: 150000 | D6: 150000 | E6: 150000 | F6: 150000 | G6: =SUM(B6:F6) | H6: =IF(G6='Répartition'!C6,"OK","À revoir")
A7: Publicité Google (recherche) | B7: 0 | C7: 125000 | D7: 125000 | E7: 125000 | F7: 125000 | G7: =SUM(B7:F7) | H7: =IF(G7='Répartition'!C7,"OK","À revoir")
A8: Presse économique en ligne | B8: 0 | C8: 0 | D8: 350000 | E8: 350000 | F8: 0 | G8: =SUM(B8:F8) | H8: =IF(G8='Répartition'!C8,"OK","À revoir")
A9: Coffrets « Au 7e jour » aux décideurs | B9: 200000 | C9: 200000 | D9: 0 | E9: 0 | F9: 0 | G9: =SUM(B9:F9) | H9: =IF(G9='Répartition'!C9,"OK","À revoir")
A10: Production des contenus | B10: 600000 | C10: 100000 | D10: 0 | E10: 0 | F10: 0 | G10: =SUM(B10:F10) | H10: =IF(G10='Répartition'!C10,"OK","À revoir")
A11: Réserve | B11: 0 | C11: 0 | D11: 0 | E11: 250000 | F11: 250000 | G11: =SUM(B11:F11) | H11: =IF(G11='Répartition'!C11,"OK","À revoir")
A12: Total de la semaine | B12: =SUM(B5:B11) | C12: =SUM(C5:C11) | D12: =SUM(D5:D11) | E12: =SUM(E5:E11) | F12: =SUM(F5:F11) | G12: =SUM(G5:G11)
A13: Cumul engagé | B13: =SUM($B$12:B12) | C13: =SUM($B$12:C12) | D13: =SUM($B$12:D12) | E13: =SUM($B$12:E12) | F13: =SUM($B$12:F12)
A15: Les rendez-vous du mois
A16: Date | B16: Ce qui se passe | H16: Qui décide
A17: Lun. 14 déc. 2026 | B17: Validation du plan, des 40 décideurs et des devis (presse, coffrets, tournage) | H17: Direction
A18: Ven. 8 janv. 2027 | B18: Contenus livrés, publicités paramétrées et relues, rien n'est lancé | H18: Cheffe de projet
A19: Lun. 11 janv. | B19: Lancement des publicités LinkedIn, Facebook, Instagram et Google | H19: Direction (feu vert)
A20: Mar. 12 janv. | B20: Lettre d'information aux clients et prospects | H20: Cheffe de projet
A21: Semaine du 18 janv. | B21: Livraison des 40 coffrets ; 1er article sponsorisé | H21: Cheffe de projet
A22: Lun. 25 janv. | B22: Point à mi-parcours : déblocage de la réserve sur le meilleur canal | H22: Direction
A23: Semaine du 25 janv. | B23: 2e article sponsorisé et insertion en lettre d'information ; relance téléphonique des coffrets | H23: Cheffe de projet
A24: Lun. 8 févr. | B24: Bilan du mois : coût par demande, rendez-vous, devis envoyés ; suite à donner | H24: Direction

Sheet Estimations
C1: Ce que le budget peut produire
C2: Les cases orange sont des hypothèses de départ : remplacez-les par les chiffres réels des régies après la 1re semaine, tout se recalcule.
A4: Support | B4: Budget | C4: Coût pour 1 000 vues (F) | D4: Vues estimées | E4: Taux de clic | F4: Clics estimés | G4: Taux de demande | H4: Demandes estimées | I4: Coût par demande
A5: Publicité LinkedIn | B5: ='Répartition'!C5 | C5: 9000 | D5: =B5/C5*1000 | E5: 0.006 | F5: =D5*E5 | G5: 0.08 | H5: =F5*G5 | I5: =IFERROR(B5/H5,0)
A6: Publicité Facebook et Instagram | B6: ='Répartition'!C6 | C6: 1500 | D6: =B6/C6*1000 | E6: 0.008 | F6: =D6*E6 | G6: 0.01 | H6: =F6*G6 | I6: =IFERROR(B6/H6,0)
A7: Publicité Google (recherche) | B7: ='Répartition'!C7 | C7: Coût par clic : 250 F | D7: — | E7: — | F7: =B7/250 | G7: 0.03 | H7: =F7*G7 | I7: =IFERROR(B7/H7,0)
A8: Total publicité en ligne | B8: =SUM(B5:B7) | H8: =SUM(H5:H7) | I8: =B8/H8
A9: Part des demandes réellement qualifiées (budget, date, décideur) | G9: 0.35 | H9: =H8*G9 | I9: =B8/H9
A11: Les objectifs du mois, tous canaux confondus
A12: Étape | B12: Objectif | C12: Comment on compte
A13: Demandes de devis qualifiées | B13: 25 | C13: Tableau de suivi des demandes : budget, date et décideur identifiés
A14: Rendez-vous tenus | B14: 12 | C14: Agenda de la cheffe de projet et de la direction
A15: Devis envoyés | B15: 10 | C15: Logiciel de devis
A16: Contrats signés sous 60 jours | B16: 4 | C16: Bons de commande reçus avant le 8 avril 2027
A17: Plafond de coût | B17: 200 000 F par demande qualifiée en moyenne | C17: Budget total dépensé ÷ demandes qualifiées
A19: Lecture : le mois ne se juge pas aux vues ni aux mentions « j'aime », mais aux demandes qualifiées et aux rendez-vous. Un seul contrat de soirée d'entreprise moyen peut couvrir une bonne part du budget : le tableau de suivi des demandes doit donc noter, pour chaque contrat, d'où venait le client.

Sheet Pilotage et risques
C1: Pilotage, risques et décisions à prendre
C2: Point de suivi chaque lundi à 9 h, du 18 janvier au 8 février.
A4: Indicateur suivi chaque lundi | B4: Source | C4: Seuil d'alerte | D4: Action
A5: Coût par demande qualifiée, par canal | B5: Régies publicitaires + tableau des demandes | C5: Plus de 150 000 F sur 7 jours | D5: Couper l'annonce, garder la meilleure version
A6: Délai de réponse aux demandes | B6: WhatsApp Business et boîte de réception | C6: Plus de 2 heures ouvrées | D6: Renfort de la permanence commerciale
A7: Rythme de dépense | B7: Onglet Calendrier, ligne « Cumul engagé » | C7: Plus de 10 % d'écart avec le prévu | D7: Réajuster les plafonds quotidiens
A8: Rendez-vous obtenus par les coffrets | B8: Agenda | C8: Moins de 3 à la fin de la semaine 3 | D8: Relance téléphonique ciblée par la direction
A9: Visites du site depuis la presse | B9: Statistiques du site (lien suivi) | C9: Moins de 100 par article | D9: Pas de 3e article ; budget basculé en réserve
A11: Les risques
A12: Risque | B12: Probabilité | C12: Ce qu'on prévoit
A13: Publicité LinkedIn plus chère que prévu | B13: Moyenne | C13: Recalage après 7 jours ; bascule vers Google et la prospection directe si le coût dépasse le plafond
A14: Contenus pas prêts le 11 janvier (équipe prise par les événements de fin d'année) | B14: Élevée | C14: Tournage fixé en décembre sur des événements déjà prévus ; date limite de livraison au 8 janvier
A15: Clients filmés qui refusent la diffusion | B15: Moyenne | C15: Accord écrit avant tournage ; coulisses sans visage ni logo client en remplacement
A16: Afflux de petites demandes urgentes non rentables | B16: Moyenne | C16: Budget minimum affiché dans le formulaire ; frais d'urgence mentionnés dans les devis
A17: Coffrets livrés à la mauvaise personne | B17: Faible | C17: Liste vérifiée par appel avant livraison ; livraison en main propre par coursier
A19: Les décisions à prendre avant le 14 décembre 2026
A20: 1. Valider le mois de diffusion (11 janvier au 7 février 2027) et la répartition des 5 000 000 F.
A21: 2. Dire si ce budget s'ajoute au plan du premier trimestre ou le remplace.
A22: 3. Valider la liste des 40 décideurs qui reçoivent un coffret.
A23: 4. Choisir les 4 événements filmés et obtenir l'accord écrit des clients.
A24: 5. Valider le budget minimum d'un événement affiché dans le formulaire de devis.
A25: 6. Autoriser les demandes de devis (presse, coffrets, tournage). Aucun achat n'est engagé sans votre accord écrit.
